LICENSE
README.md
setup.py
pyroprompts_client/__init__.py
pyroprompts_client/client.py
pyroprompts_client/exceptions.py
pyroprompts_client.egg-info/PKG-INFO
pyroprompts_client.egg-info/SOURCES.txt
pyroprompts_client.egg-info/dependency_links.txt
pyroprompts_client.egg-info/requires.txt
pyroprompts_client.egg-info/top_level.txt