Metadata-Version: 2.1
Name: pyroprompts-client
Version: 0.1.2
Summary: PyroPrompts Client for Python
Home-page: https://github.com/pyroprompts/pyroprompts-client
Author: Matt Ferrante
Author-email: matt@pyroprompts.com
License: MIT
License-File: LICENSE
